jupyter_tabnine/__init__.py
jupyter_tabnine/_version.py
jupyter_tabnine/handler.py
jupyter_tabnine/tabnine.py
jupyter_tabnine/static/README.md
jupyter_tabnine/static/main.css
jupyter_tabnine/static/main.js
jupyter_tabnine/static/tabnine.yaml
jupyter_tabnine-1.2.3.data/data/static/README.md
jupyter_tabnine-1.2.3.data/data/static/main.css
jupyter_tabnine-1.2.3.data/data/static/main.js
jupyter_tabnine-1.2.3.data/data/static/tabnine.yaml
jupyter_tabnine-1.2.3.dist-info/LICENSE
jupyter_tabnine-1.2.3.dist-info/METADATA
jupyter_tabnine-1.2.3.dist-info/WHEEL
jupyter_tabnine-1.2.3.dist-info/top_level.txt
jupyter_tabnine-1.2.3.dist-info/RECORD
