Metadata-Version: 2.1
Name: jupyter-tabnine
Version: 1.2.3
Summary: Jupyter notebook extension which support coding auto-completion based on Deep Learning
Home-page: https://github.com/wenmin-wu/jupyter-tabnine
Author: Wenmin Wu
Author-email: wuwenmin1991@gmail.com
License: MIT
Platform: UNKNOWN
Classifier: Framework :: Jupyter
Requires-Python: >=3.5
